impractipy/__init__.py
impractipy/pseudonyms.py
impractipy-0.1.dist-info/LICENSE
impractipy-0.1.dist-info/METADATA
impractipy-0.1.dist-info/WHEEL
impractipy-0.1.dist-info/top_level.txt
impractipy-0.1.dist-info/RECORD
