Metadata-Version: 2.1
Name: impractipy
Version: 0.1
Summary: Collection of impractical Python projects
License-File: LICENSE
